ssh_python/__init__.py
ssh_python/__main__.py
ssh_python/conn.py
ssh_python/shell.py
ssh_python/ssh_methods.py
shell_ssh_client-0.0.1.dist-info/METADATA
shell_ssh_client-0.0.1.dist-info/WHEEL
shell_ssh_client-0.0.1.dist-info/entry_points.txt
shell_ssh_client-0.0.1.dist-info/top_level.txt
shell_ssh_client-0.0.1.dist-info/RECORD
