Metadata-Version: 2.1
Name: shell-ssh-client
Version: 0.0.1
Summary: ssh shell demo on python
Project-URL: Homepage, https://github.com/Yulai202020/ssh-python
Project-URL: Documentation, https://github.com/Yulai202020/ssh-python
Project-URL: Changes, https://github.com/Yulai202020/ssh-python
Keywords: ssh,project
Requires-Python: >=3.10
Requires-Dist: paramiko
